{"duration": 0.1575009822845459, "input_args": {"conc_vector": "array([0, 0, 0, 6, 0, 0, 0, 6, 0, 0, 0, 6, 0, 0, 0, 6, 0, 0, 0, 6, 0, 0,\n       0, 6, 0, 0, 0, 6, 0, 0, 0, 6, 0, 0, 0, 6, 0, 0, 0, 6, 0, 0, 0, 6,\n       0, 0, 0, 6, 0, 0, 0, 6, 0, 0, 0, 6, 0, 0, 0, 6, 0, 0, 0, 6, 0, 0,\n       0, 6, 0, 0, 0, 6, 0, 0, 0, 6, 2, 0, 0, 4, 0, 0, 0, 6, 0, 0, 0, 6,\n       0, 0, 0, 6, 0, 0, 0, 6, 0, 0, 0, 6, 0, 0, 0, 6, 0, 0, 0, 6, 0, 0,\n       0, 6, 0, 0, 0, 6, 0, 0, 0, 6, 0, 0, 0, 6, 0, 0, 0, 6, 0, 0, 0, 6,\n       0, 0, 0, 6, 0, 0, 0, 6, 0, 0, 0, 6, 0, 0, 0, 6, 0, 0, 0, 6, 0, 0,\n       0, 6, 0, 0, 0, 6, 0, 0, 0, 6, 0, 0, 0, 6, 0, 0, 0, 6, 0, 0, 0, 6,\n       0, 0, 0, 6, 0, 0, 0, 6, 0, 0, 0, 6, 0, 0, 0, 6, 0, 0, 0, 6, 0, 0,\n       0, 6, 0, 0, 0, 6, 0, 0, 0, 6, 0, 0, 0, 6, 0, 0, 0, 6, 0, 0, 0, 6,\n       0, 0, 0, 6, 0, 0, 0, 6, 0, 0, 0, 6, 0, 0, 0, 6, 0, 0, 0, 6, 0, 0,\n       0, 6, 0, 0, 0, 6, 0, 0, 0, 6, 0, 1, 0, 5, 0, 0, 0, 6, 0, 0, 0, 6,\n       0, 0, 0, 6, 0, 0, 0, 6, 0, 0, 0, 6, 0, 0, 0, 6, 0, 0, 0, 6, 0, 0,\n       0, 6, 0, 0, 0, 6, 0, 0, 0, 6, 0, 0, 0, 6, 0, 0, 0, 6, 0, 0, 0, 6,\n       0, 0, 0, 6, 1, 0, 0, 5, 2, 0, 0, 4, 0, 0, 0, 6, 0, 0, 0, 6, 0, 0,\n       0, 6, 0, 0, 0, 6, 0, 0, 0, 6, 0, 0, 0, 6, 0, 0, 0, 6, 0, 0, 0, 6,\n       0, 0, 0, 6, 0, 0, 0, 6, 0, 0, 0, 6, 0, 0, 0, 6, 0, 0, 0, 6, 0, 0,\n       0, 6, 0, 0, 0, 6, 0, 0, 0, 6, 0, 0, 0, 6, 0, 0, 0, 6, 0, 0, 0, 6,\n       0, 0, 0, 6])", "n_tests": "2", "n_boot": "100000", "prior_freq": "0.0015762866789784916"}}