{"duration": 0.16257071495056152, "input_args": {"conc_vector": "array([ 0,  0,  0, 94,  0,  0,  0, 94,  0,  0,  0, 94,  0,  0,  0, 94,  0,\n        0,  0, 94,  0,  0,  0, 94,  0,  0,  0, 94,  0,  0,  0, 94,  0,  0,\n        0, 94,  0,  0,  0, 94,  0,  0,  0, 94,  0,  0,  0, 94,  0,  0,  0,\n       94,  0,  0,  0, 94,  0,  0,  0, 94,  0,  0,  0, 94,  0,  0,  0, 94,\n        0,  0,  0, 94,  0,  0,  0, 94,  1,  0,  0, 93,  0,  0,  0, 94,  0,\n        0,  0, 94,  0,  0,  0, 94,  0,  0,  0, 94,  0,  0,  0, 94,  0,  0,\n        0, 94,  1,  0,  0, 93,  0,  0,  0, 94,  0,  0,  0, 94,  0,  0,  0,\n       94,  0,  0,  0, 94,  0,  0,  0, 94,  0,  0,  0, 94,  0,  0,  0, 94,\n        0,  0,  0, 94,  0,  0,  0, 94,  0,  0,  0, 94,  0,  0,  0, 94,  0,\n        0,  0, 94,  0,  0,  0, 94,  0,  0,  0, 94,  0,  0,  0, 94,  0,  0,\n        0, 94,  0,  0,  0, 94,  0,  0,  0, 94,  0,  0,  0, 94,  1,  0,  0,\n       93,  0,  0,  0, 94,  0,  0,  0, 94,  0,  0,  0, 94,  0,  0,  0, 94,\n        0,  0,  0, 94,  0,  0,  0, 94,  0,  0,  0, 94,  0,  0,  0, 94,  0,\n        0,  0, 94,  0,  0,  0, 94,  0,  0,  0, 94,  0,  0,  0, 94,  0,  0,\n        0, 94,  0,  0,  0, 94,  0,  0,  0, 94,  0,  0,  0, 94,  0,  0,  0,\n       94,  0,  0,  0, 94,  0,  0,  0, 94,  0,  0,  0, 94,  0,  0,  0, 94,\n        0,  0,  0, 94,  0,  0,  0, 94,  0,  0,  0, 94,  1,  0,  0, 93,  0,\n        0,  0, 94,  0,  0,  0, 94,  0,  0,  0, 94,  0,  0,  0, 94,  0,  0,\n        0, 94,  0,  0,  0, 94,  0,  0,  0, 94,  0,  0,  0, 94,  0,  0,  0,\n       94,  1,  0,  0, 93,  0,  0,  0, 94,  0,  0,  0, 94,  0,  0,  0, 94,\n        0,  0,  0, 94,  0,  0,  0, 94,  0,  0,  0, 94,  0,  0,  0, 94,  0,\n        0,  0, 94,  0,  0,  0, 94,  1,  0,  0, 93,  0,  0,  0, 94,  0,  0,\n        0, 94,  0,  0,  0, 94,  0,  0,  0, 94,  0,  0,  0, 94,  0,  0,  0,\n       94,  0,  0,  0, 94,  0,  0,  0, 94])", "n_tests": "2", "n_boot": "100000", "prior_freq": "8.9e-05"}}